setup.py
venv/Lib/site-packages/xlsxwriter/__init__.py
venv/Lib/site-packages/xlsxwriter/app.py
venv/Lib/site-packages/xlsxwriter/chart.py
venv/Lib/site-packages/xlsxwriter/chart_area.py
venv/Lib/site-packages/xlsxwriter/chart_bar.py
venv/Lib/site-packages/xlsxwriter/chart_column.py
venv/Lib/site-packages/xlsxwriter/chart_doughnut.py
venv/Lib/site-packages/xlsxwriter/chart_line.py
venv/Lib/site-packages/xlsxwriter/chart_pie.py
venv/Lib/site-packages/xlsxwriter/chart_radar.py
venv/Lib/site-packages/xlsxwriter/chart_scatter.py
venv/Lib/site-packages/xlsxwriter/chart_stock.py
venv/Lib/site-packages/xlsxwriter/chartsheet.py
venv/Lib/site-packages/xlsxwriter/comments.py
venv/Lib/site-packages/xlsxwriter/compat_collections.py
venv/Lib/site-packages/xlsxwriter/compatibility.py
venv/Lib/site-packages/xlsxwriter/contenttypes.py
venv/Lib/site-packages/xlsxwriter/core.py
venv/Lib/site-packages/xlsxwriter/custom.py
venv/Lib/site-packages/xlsxwriter/drawing.py
venv/Lib/site-packages/xlsxwriter/exceptions.py
venv/Lib/site-packages/xlsxwriter/format.py
venv/Lib/site-packages/xlsxwriter/packager.py
venv/Lib/site-packages/xlsxwriter/relationships.py
venv/Lib/site-packages/xlsxwriter/shape.py
venv/Lib/site-packages/xlsxwriter/sharedstrings.py
venv/Lib/site-packages/xlsxwriter/styles.py
venv/Lib/site-packages/xlsxwriter/table.py
venv/Lib/site-packages/xlsxwriter/theme.py
venv/Lib/site-packages/xlsxwriter/utility.py
venv/Lib/site-packages/xlsxwriter/vml.py
venv/Lib/site-packages/xlsxwriter/workbook.py
venv/Lib/site-packages/xlsxwriter/worksheet.py
venv/Lib/site-packages/xlsxwriter/xmlwriter.py
xlsxutils.egg-info/PKG-INFO
xlsxutils.egg-info/SOURCES.txt
xlsxutils.egg-info/dependency_links.txt
xlsxutils.egg-info/top_level.txt