Metadata-Version: 1.0
Name: xlsxutils
Version: 0.1
Summary: Excel Generator utils
Home-page: https://github.com/goldinger/xlsxutils.git
Author: asghir121317
Author-email: amine@sghir.me
License: Apache 2.0
Platform: UNKNOWN
